fastfuels/__init__.py
fastfuels/core.py
fastfuels/fastfuels_create_index.py
fastfuels-1.0.7.data/scripts/fastfuels_create_index.py
fastfuels-1.0.7.dist-info/LICENSE.txt
fastfuels-1.0.7.dist-info/METADATA
fastfuels-1.0.7.dist-info/WHEEL
fastfuels-1.0.7.dist-info/top_level.txt
fastfuels-1.0.7.dist-info/RECORD
