Metadata-Version: 2.1
Name: fastfuels
Version: 1.0.7
Summary: 3D fuelscapes for the contiguous US
Home-page: https://github.com/teamholtz/FastFuels-Python
Author: Holtz Technology and Development Services LLC
Author-email: lucas@holtztds.com
License: GNU GPLv3
Keywords: fire model,fuelscape,wildfire
Classifier: Development Status :: 3 - Alpha
Classifier: Intended Audience :: Developers
Classifier: License :: OSI Approved :: GNU General Public License v3 (GPLv3)
Classifier: Programming Language :: Python :: 3
Classifier: Programming Language :: Python :: 3.4
Classifier: Programming Language :: Python :: 3.5
Classifier: Programming Language :: Python :: 3.6
License-File: LICENSE.txt
Requires-Dist: colorcet ==2.0.6
Requires-Dist: fsspec ==2024.2.0
Requires-Dist: msgpack ==1.0.2
Requires-Dist: numpy ==1.23.0
Requires-Dist: pyvista ==0.28.1
Requires-Dist: s3fs ==2024.2.0
Requires-Dist: scipy ==1.11.4
Requires-Dist: shapely <2
Requires-Dist: zarr ==2.8.3
